usercheck/AbstractService.py
usercheck/UsernameChecker.py
usercheck/__init__.py
usercheck/services/Github.py
usercheck/services/Instagram.py
usercheck/services/Reddit.py
usercheck/services/Twitter.py
usercheck/services/__init__.py
usercheck-1.0.dist-info/METADATA
usercheck-1.0.dist-info/RECORD
usercheck-1.0.dist-info/WHEEL
usercheck-1.0.dist-info/entry_points.txt
usercheck-1.0.dist-info/top_level.txt
