Metadata-Version: 2.1
Name: usercheck
Version: 1.0
Summary: Check if your username is taken from various sites
Home-page: https://github.com/ethanquix/userchecker
Author: Dimitri Wyzlic
Author-email: dimitriwyzlic@gmail.com
License: MIT
Platform: UNKNOWN
Requires-Dist: requests
